rsynccheck/__init__.py
rsynccheck/cli.py
rsynccheck/rsynccheck.py
rsynccheck/utilities/__init__.py
rsynccheck/utilities/base_types.py
rsynccheck/utilities/error_utils.py
rsynccheck/utilities/log.py
rsynccheck-0.1.0.dist-info/LICENSE.md
rsynccheck-0.1.0.dist-info/METADATA
rsynccheck-0.1.0.dist-info/WHEEL
rsynccheck-0.1.0.dist-info/entry_points.txt
rsynccheck-0.1.0.dist-info/top_level.txt
rsynccheck-0.1.0.dist-info/RECORD
